CONTRIBUTORS.txt
MANIFEST.in
README.rst
setup.py
docs/HISTORY.txt
docs/INSTALL.txt
docs/LICENSE.GPL
docs/LICENSE.txt
redturtle/__init__.py
redturtle.sqlcontents.egg-info/PKG-INFO
redturtle.sqlcontents.egg-info/SOURCES.txt
redturtle.sqlcontents.egg-info/dependency_links.txt
redturtle.sqlcontents.egg-info/entry_points.txt
redturtle.sqlcontents.egg-info/namespace_packages.txt
redturtle.sqlcontents.egg-info/not-zip-safe
redturtle.sqlcontents.egg-info/requires.txt
redturtle.sqlcontents.egg-info/top_level.txt
redturtle/sqlcontents/README.txt
redturtle/sqlcontents/__init__.py
redturtle/sqlcontents/config.py
redturtle/sqlcontents/configure.zcml
redturtle/sqlcontents/i18n.sh
redturtle/sqlcontents/adapters/__init__.py
redturtle/sqlcontents/adapters/configure.zcml
redturtle/sqlcontents/adapters/engine.py
redturtle/sqlcontents/browser/__init__.py
redturtle/sqlcontents/browser/configure.zcml
redturtle/sqlcontents/browser/sqlquery_view.pt
redturtle/sqlcontents/browser/sqlquery_view.py
redturtle/sqlcontents/browser/images/sqlfolder_icon.png
redturtle/sqlcontents/browser/images/sqlquery_icon.png
redturtle/sqlcontents/content/__init__.py
redturtle/sqlcontents/content/configure.zcml
redturtle/sqlcontents/content/sqlfolder.py
redturtle/sqlcontents/content/sqlquery.py
redturtle/sqlcontents/interfaces/__init__.py
redturtle/sqlcontents/interfaces/sqlfolder.py
redturtle/sqlcontents/interfaces/sqlquery.py
redturtle/sqlcontents/locales/manual.pot
redturtle/sqlcontents/locales/redturtle.sqlcontents.pot
redturtle/sqlcontents/locales/it/LC_MESSAGES/redturtle.sqlcontents.po
redturtle/sqlcontents/profiles/default/factorytool.xml
redturtle/sqlcontents/profiles/default/metadata.xml
redturtle/sqlcontents/profiles/default/rolemap.xml
redturtle/sqlcontents/profiles/default/types.xml
redturtle/sqlcontents/profiles/default/types/SQLFolder.xml
redturtle/sqlcontents/profiles/default/types/SQLQuery.xml
redturtle/sqlcontents/tests/__init__.py
redturtle/sqlcontents/tests/base.py
redturtle/sqlcontents/tests/lipsum.db
redturtle/sqlcontents/tests/test_doctest.py